bedrock_server_manager/__init__.py
bedrock_server_manager/__main__.py
bedrock_server_manager/context.py
bedrock_server_manager/error.py
bedrock_server_manager/logging.py
bedrock_server_manager/api/__init__.py
bedrock_server_manager/api/addon.py
bedrock_server_manager/api/application.py
bedrock_server_manager/api/backup_restore.py
bedrock_server_manager/api/info.py
bedrock_server_manager/api/misc.py
bedrock_server_manager/api/player.py
bedrock_server_manager/api/plugins.py
bedrock_server_manager/api/server.py
bedrock_server_manager/api/server_install_config.py
bedrock_server_manager/api/settings.py
bedrock_server_manager/api/system.py
bedrock_server_manager/api/utils.py
bedrock_server_manager/api/web.py
bedrock_server_manager/api/world.py
bedrock_server_manager/cli/__init__.py
bedrock_server_manager/cli/cleanup.py
bedrock_server_manager/cli/database.py
bedrock_server_manager/cli/generate_password.py
bedrock_server_manager/cli/migrate.py
bedrock_server_manager/cli/reset_password.py
bedrock_server_manager/cli/service.py
bedrock_server_manager/cli/setup.py
bedrock_server_manager/cli/utils.py
bedrock_server_manager/cli/web.py
bedrock_server_manager/config/__init__.py
bedrock_server_manager/config/bcm_config.py
bedrock_server_manager/config/blocked_commands.py
bedrock_server_manager/config/const.py
bedrock_server_manager/config/settings.py
bedrock_server_manager/config/splash_text.py
bedrock_server_manager/core/__init__.py
bedrock_server_manager/core/bedrock_process_manager.py
bedrock_server_manager/core/bedrock_server.py
bedrock_server_manager/core/downloader.py
bedrock_server_manager/core/manager.py
bedrock_server_manager/core/utils.py
bedrock_server_manager/core/manager_mixins/__init__.py
bedrock_server_manager/core/manager_mixins/content_mixin.py
bedrock_server_manager/core/manager_mixins/discovery_mixin.py
bedrock_server_manager/core/manager_mixins/player_mixin.py
bedrock_server_manager/core/manager_mixins/system_mixin.py
bedrock_server_manager-3.7.2.dist-info/licenses/LICENSE
bedrock_server_manager-3.7.2.dist-info/METADATA
bedrock_server_manager-3.7.2.dist-info/WHEEL
bedrock_server_manager-3.7.2.dist-info/entry_points.txt
bedrock_server_manager-3.7.2.dist-info/top_level.txt
bedrock_server_manager-3.7.2.dist-info/RECORD
