Metadata-Version: 2.4
Name: bedrock-server-manager
Version: 3.7.2
Summary: A manager for Minecraft Bedrock Dedicated Servers
Author-email: DMedina559 <dmedina559-github@outlook.com>
Project-URL: Repository, https://github.com/dmedina559/bedrock-server-manager.git
Project-URL: Bug Tracker, https://github.com/DMedina559/bedrock-server-manager/issues
Project-URL: Changelog, https://bedrock-server-manager.readthedocs.io/en/latest/changelog.html
Keywords: minecraft,bedrock,server,manager,bsm,admin,dashboard,web,fastapi
Classifier: Programming Language :: Python :: 3
Classifier: Programming Language :: Python :: 3.10
Classifier: Programming Language :: Python :: 3.11
Classifier: Programming Language :: Python :: 3.12
Classifier: Programming Language :: Python :: 3.13
Classifier: Operating System :: OS Independent
Classifier: Environment :: Console
Classifier: Topic :: Games/Entertainment
Requires-Python: >=3.10
License-File: LICENSE
Requires-Dist: requests<2.33,>=2.32.3
Requires-Dist: psutil<7.3,>=7.0.0
Requires-Dist: pywin32<312,>=310; sys_platform == "win32"
Requires-Dist: click<8.4,>=8.2.0
Requires-Dist: questionary<2.2,>=2.1.0
Requires-Dist: fastapi<0.129,>=0.115.0
Requires-Dist: uvicorn[standard]<0.41,>=0.35.0
Requires-Dist: python-jose[cryptography]<3.6,>=3.5.0
Requires-Dist: jinja2<3.2,>=3.1.0
Requires-Dist: python_multipart<0.1,>=0.0.20
Requires-Dist: bcrypt<5.1,>=5.0.0
Requires-Dist: sqlalchemy<2.1,>=2.0.0
Requires-Dist: appdirs<1.5,>=1.4.4
Requires-Dist: alembic<1.19,>=1.16
Requires-Dist: mcstatus<12.1,>=12.0
Provides-Extra: dev
Requires-Dist: pytest<9.1,>=8.4.0; extra == "dev"
Requires-Dist: pytest-mock<3.16,>=3.14.0; extra == "dev"
Requires-Dist: black<25.13,>=25.1.0; extra == "dev"
Requires-Dist: flake8<7.4,>=7.3.0; extra == "dev"
Requires-Dist: httpx<0.29,>=0.28.0; extra == "dev"
Requires-Dist: pytest-asyncio<1.4,>=1.1.0; extra == "dev"
Requires-Dist: isort<7.1,>=5.13.0; extra == "dev"
Requires-Dist: mypy<1.20,>=1.10.0; extra == "dev"
Provides-Extra: cli
Requires-Dist: bsm-api-client[cli]<1.4.0,>=1.2.1; extra == "cli"
Provides-Extra: docs
Requires-Dist: sphinx<9.2,>=8.2.0; extra == "docs"
Requires-Dist: sphinx-click<6.3,>=6.0.0; extra == "docs"
Requires-Dist: myst-parser<4.1,>=4.0.0; extra == "docs"
Requires-Dist: sphinx-rtd-theme<3.2,>=3.0.0; extra == "docs"
Requires-Dist: sphinx-github-changelog<1.8,>=1.7.0; extra == "docs"
Provides-Extra: mysql
Requires-Dist: mysqlclient<2.3,>=2.2.7; extra == "mysql"
Requires-Dist: PyMySQL<1.2,>=1.1.1; extra == "mysql"
Provides-Extra: mariadb
Requires-Dist: mariadb<1.2,>=1.1.13; extra == "mariadb"
Requires-Dist: PyMySQL<1.2,>=1.1.1; extra == "mariadb"
Provides-Extra: postgresql
Requires-Dist: psycopg<3.4,>=3.2.9; extra == "postgresql"
Dynamic: license-file
